LICENSE
MANIFEST.in
README.md
cyanure.py
cyanure_wrap_module.cpp
setup.py
cyanure_openblas_no_openmp.egg-info/PKG-INFO
cyanure_openblas_no_openmp.egg-info/SOURCES.txt
cyanure_openblas_no_openmp.egg-info/dependency_links.txt
cyanure_openblas_no_openmp.egg-info/requires.txt
cyanure_openblas_no_openmp.egg-info/top_level.txt
utils/cblas_alt_template.h
utils/cblas_defvar.h
utils/data.h
utils/linalg.h
utils/list.h
utils/loss.h
utils/misc.h
utils/regul.h
utils/solvers.h
utils/utils.h
utils/wrapper_utils.h