Metadata-Version: 1.0
Name: cyanure-openblas-no-openmp
Version: 0.21.post3
Summary: optimization toolbox for machine learning
Home-page: http://julien.mairal.org/cyanure/
Author: UNKNOWN
Author-email: julien.mairal@inria.fr
License: bsd-3-clause
Platform: UNKNOWN
